<?xml version="1.0" encoding="UTF-8"?>
<!DOCTYPE mapper PUBLIC "-//mybatis.org//DTD Mapper 3.0//EN" "http://mybatis.org/dtd/mybatis-3-mapper.dtd">
<mapper namespace="com.moguying.plant.core.dao.mall.MallProductTypeDAO">
  <resultMap id="BaseResultMap" type="com.moguying.plant.core.entity.mall.MallProductType">
    <id column="id" jdbcType="INTEGER" property="id" />
    <result column="type_name" jdbcType="VARCHAR" property="typeName" />
    <result column="type_sort" jdbcType="INTEGER" property="typeSort" />
  </resultMap>
  <sql id="Base_Column_List">
    id, type_name
  </sql>

  <select id="selectSelective" resultMap="BaseResultMap">
    select <include refid="Base_Column_List"/> from plant_mall_product_type
    <where>
      <if test="id != null">
        id = #{id}
      </if>
      <if test="typeName != null">
        <bind name="typeNameLike" value="'%'+typeName+'%'"/>
        AND type_name like #{typeNameLike}
      </if>
    </where>
    order by id desc
  </select>
</mapper>